nats_request_asap/__init__.py
nats_request_asap-0.2.2.dist-info/LICENSE.txt
nats_request_asap-0.2.2.dist-info/METADATA
nats_request_asap-0.2.2.dist-info/WHEEL
nats_request_asap-0.2.2.dist-info/top_level.txt
nats_request_asap-0.2.2.dist-info/RECORD
